b3o_fedlearn/__init__.py
b3o_fedlearn/client_fedlearn.py
b3o_fedlearn/client_setup.py
b3o_fedlearn/data_processing.py
b3o_fedlearn/fedlearner.py
b3o_fedlearn-1.0.0.dist-info/LICENSE
b3o_fedlearn-1.0.0.dist-info/METADATA
b3o_fedlearn-1.0.0.dist-info/WHEEL
b3o_fedlearn-1.0.0.dist-info/top_level.txt
b3o_fedlearn-1.0.0.dist-info/RECORD
