Metadata-Version: 2.1
Name: b3o-fedlearn
Version: 1.0.0
Summary: a project for federated learning using AWS
Home-page: https://github.com/ACS-High-School
Author: skswjdekdud
Author-email: skswjdekdud1103@gmail.com
Project-URL: Bug Tracker, https://github.com/ACS-High-School/ML/issues
Classifier: Programming Language :: Python :: 3
Classifier: License :: OSI Approved :: MIT License
Classifier: Operating System :: OS Independent
Requires-Python: >=3.8
License-File: LICENSE
